LICENSE
README.rst
pyproject.toml
setup.cfg
setup.py
segreg/__init__.py
segreg/mockjit.py
segreg.egg-info/PKG-INFO
segreg.egg-info/SOURCES.txt
segreg.egg-info/dependency_links.txt
segreg.egg-info/requires.txt
segreg.egg-info/top_level.txt
segreg/analysis/__init__.py
segreg/analysis/stats_plotting.py
segreg/bootstrap/__init__.py
segreg/bootstrap/bootstrap_methods.py
segreg/bootstrap/confidence_intervals.py
segreg/bootstrap/resampling.py
segreg/bootstrap/tests/__init__.py
segreg/bootstrap/tests/test_bootstrap_methods.py
segreg/bootstrap/tests/test_resampling.py
segreg/data/__init__.py
segreg/data/_datasets.py
segreg/data/_testing_util.py
segreg/model/__init__.py
segreg/model/estimator.py
segreg/model/ols_estimator.py
segreg/model/one_bkpt_segreg.cpp
segreg/model/regression.c
segreg/model/segreg_estimator.py
segreg/model/two_bkpt_segreg.c
segreg/model/alt/__init__.py
segreg/model/alt/brute_force_segreg.py
segreg/model/alt/likelihood_util.py
segreg/model/alt/one_bkpt_segreg_alt.py
segreg/model/alt/regression_alt.py
segreg/model/alt/two_bkpt_segreg_alt.py
segreg/model/alt/two_bkpt_segreg_alt_SLOW.py
segreg/model/alt/tests/__init__.py
segreg/model/alt/tests/test_one_bkpt_segreg_alt.py
segreg/model/alt/tests/test_regression_alt.py
segreg/model/alt/tests/test_two_bkpt_segreg_alt.py
segreg/model/tests/__init__.py
segreg/model/tests/one_bkpt_segreg_examples.py
segreg/model/tests/one_bkpt_segreg_helper.py
segreg/model/tests/test_hinkley_tieout.py
segreg/model/tests/test_ols_estimator.py
segreg/model/tests/test_one_bkpt_segreg.py
segreg/model/tests/test_one_bkpt_suite.py
segreg/model/tests/test_one_bkpt_tieouts.py
segreg/model/tests/test_regression.py
segreg/model/tests/test_segmented_regression.py
segreg/model/tests/test_segmented_regression_estimator.py
segreg/model/tests/test_segmented_regression_tieout.py
segreg/model/tests/test_two_bkpt_segreg.py
segreg/model/tests/test_two_bkpt_suite.py
segreg/model/tests/two_bkpt_segreg_examples.py
segreg/model/tests/two_bkpt_segreg_helper.py