Metadata-Version: 2.1
Name: segreg
Version: 0.0.3
Summary: Segmented regression models
Home-page: https://github.com/stevelill/segreg
Author: Steven Lillywhite
Author-email: stevelill005@gmail.com
License: BSD 3-Clause License
Platform: UNKNOWN
Classifier: Programming Language :: Python :: 3
Classifier: Programming Language :: Python :: Implementation :: CPython
Classifier: License :: OSI Approved :: BSD License
Classifier: Operating System :: OS Independent
Classifier: Development Status :: 3 - Alpha
Classifier: Intended Audience :: Science/Research
Classifier: Topic :: Scientific/Engineering
Requires-Python: >=3.8
License-File: LICENSE
